Metadata-Version: 2.4
Name: testlibcalc
Version: 1.0
Summary: Uma biblioteca de exemplo simples para ensino
Home-page: https://github.com/adrillima/testlibcalc
Author: math
Author-email: adrillima455@gmail.com
Classifier: Programming Language :: Python :: 3
Classifier: License :: OSI Approved :: MIT License
Classifier: Natural Language :: Portuguese (Brazilian)
Requires-Python: >=3.6
License-File: LICENSE.txt
Dynamic: author
Dynamic: author-email
Dynamic: classifier
Dynamic: description
Dynamic: description-content-type
Dynamic: home-page
Dynamic: license-file
Dynamic: requires-python
Dynamic: summary
